argparse_with_config/__init__.py
argparse_with_config/tests/test_basics.py
argparse_with_config/tests/test_config_files.py
argparse_with_config/tests/test_groupings.py
argparse_with_config-0.1.5.dist-info/METADATA
argparse_with_config-0.1.5.dist-info/WHEEL
argparse_with_config-0.1.5.dist-info/licenses/LICENSE.txt
argparse_with_config-0.1.5.dist-info/RECORD
