Metadata-Version: 2.3
Name: argparse-with-config
Version: 0.1.5
Summary: A version (wrapper) of argparse that handles reading configuration files.
Project-URL: Homepage, https://github.com/hardaker/argparse-with-config
License: Copyright 2024 Wes Hardaker
License-File: LICENSE.txt
Requires-Python: >=3.10
Requires-Dist: dotnest>=1.1
Requires-Dist: pyaml
Requires-Dist: rich
Requires-Dist: rich-argparse
Requires-Dist: rich-logging
